LFPy/__init__.py
LFPy/alias_method.py
LFPy/alias_method.pyx
LFPy/cell.py
LFPy/eegmegcalc.py
LFPy/inputgenerators.py
LFPy/network.py
LFPy/pointprocess.py
LFPy/run_simulation.py
LFPy/run_simulation.pyx
LFPy/templatecell.py
LFPy/tools.py
LFPy/version.py
LFPy/test/L23E_p23.hoc
LFPy/test/__init__.py
LFPy/test/ball_and_stick_template.hoc
LFPy/test/ball_and_sticks.hoc
LFPy/test/ball_and_sticks_w_lists.hoc
LFPy/test/common.py
LFPy/test/expsyni.mod
LFPy/test/fem_mix_dip.npz
LFPy/test/sinsyn.mod
LFPy/test/stick.hoc
LFPy/test/stick_template.hoc
LFPy/test/sticks_not_connected_head_to_toe.hoc
LFPy/test/test_alias_method.py
LFPy/test/test_cell.py
LFPy/test/test_eegmegcalc.py
LFPy/test/test_imem.py
LFPy/test/test_inputgenerators.py
LFPy/test/test_lfpcalc.py
LFPy/test/test_misc.py
LFPy/test/test_morphology_import.py
LFPy/test/test_network.py
LFPy/test/test_networkcell.py
LFPy/test/test_pointprocess.py
LFPy/test/test_recextelectrode.py
LFPy/test/test_templatecell.py
LFPy/test/test_tools.py
lfpy-2.3.6.dist-info/licenses/LICENSE
lfpy-2.3.6.dist-info/METADATA
lfpy-2.3.6.dist-info/WHEEL
lfpy-2.3.6.dist-info/top_level.txt
lfpy-2.3.6.dist-info/RECORD
