Metadata-Version: 2.4
Name: LFPy
Version: 2.3.6
Summary: A module for modeling extracellular potentials of multicompartment neuron models built on NEURON
Home-page: http://LFPy.readthedocs.io
Download-URL: https://github.com/LFPy/LFPy/tarball/v2.3.6
Maintainer: LFPy-team
Maintainer-email: lfpy@users.noreply.github.com
License: LICENSE
Classifier: License :: OSI Approved :: GNU General Public License (GPL)
Classifier: Programming Language :: Python
Classifier: Programming Language :: Python :: 3
Classifier: Programming Language :: Python :: 3.7
Classifier: Programming Language :: Python :: 3.8
Classifier: Programming Language :: Python :: 3.9
Classifier: Programming Language :: Python :: 3.10
Classifier: Programming Language :: Python :: 3.11
Classifier: Programming Language :: Cython
Classifier: Operating System :: OS Independent
Classifier: Topic :: Scientific/Engineering
Classifier: Topic :: Scientific/Engineering :: Physics
Classifier: Topic :: Utilities
Classifier: Intended Audience :: Developers
Classifier: Intended Audience :: Science/Research
Classifier: Development Status :: 5 - Production/Stable
Provides: LFPy
License-File: LICENSE
Requires-Dist: neuron>=7.7.2
Requires-Dist: numpy>=1.8
Requires-Dist: scipy>=0.14
Requires-Dist: Cython>=0.20
Requires-Dist: h5py>=2.5
Requires-Dist: lfpykit>=0.5
Provides-Extra: tests
Requires-Dist: pytest; extra == "tests"
Provides-Extra: docs
Requires-Dist: sphinx; extra == "docs"
Requires-Dist: numpydoc; extra == "docs"
Requires-Dist: sphinx_rtd_theme; extra == "docs"
Dynamic: classifier
Dynamic: description
Dynamic: description-content-type
Dynamic: download-url
Dynamic: home-page
Dynamic: license
Dynamic: license-file
Dynamic: maintainer
Dynamic: maintainer-email
Dynamic: provides
Dynamic: provides-extra
Dynamic: requires-dist
Dynamic: summary
